LICENSE
MANIFEST.in
README.md
requirements.txt
setup.py
daam/__init__.py
daam/_version.py
daam/evaluate.py
daam/experiment.py
daam/heatmap.py
daam/hook.py
daam/trace.py
daam/utils.py
daam.egg-info/PKG-INFO
daam.egg-info/SOURCES.txt
daam.egg-info/dependency_links.txt
daam.egg-info/entry_points.txt
daam.egg-info/requires.txt
daam.egg-info/top_level.txt
daam/run/__init__.py
daam/run/demo.py
daam/run/evaluate.py
daam/run/generate.py