Metadata-Version: 2.1
Name: daam
Version: 0.0.14
Summary: What the DAAM: Interpreting Stable Diffusion Using Cross Attention.
Home-page: https://github.com/castorini/daam
Author: Raphael Tang
Author-email: r33tang@uwaterloo.ca
License: MIT
Requires-Python: >=3.8
License-File: LICENSE
